{"jobID": "2795653634", "jobLocation": "New_York_NY", "jobTitle": "Instructional Designer", "companyRating": "3.6", "companyInfo": {"Website": "www.similarweb.com", "Headquarters": "Tel Aviv-Yafo, Israel", "Size": "201 to 500 employees", "Founded": " 2008", "Type": " Company - Private", "Industry": " Information Technology", "Revenue": " Unknown / Non-Applicable", "Competitors": " comScore, App Annie, Alexa Internet"}, "estimatedSalary": "89000", "jobDescription": " SimilarWeb is the pioneer of market intelligence and the standard for understanding the digital world. SimilarWeb provides granular insights about any website or app across all industries in every region enabling the world's biggest brands like Airbnb, Walmart, HSBC, eBay and adidas to create the strategies necessary to win market share. The company has raised over $112M and has nearly 400 employees across eight global offices.  SimilarWeb has been named one of Inc.com 15 Israeli Startups to Watch in 2017 and one of Business Insiders Top 50 Enterprise Startups to Bet Your Career On.  But if we want to continue helping the worlds biggest brands reimagine what is possible online, we need talented and driven individuals who are looking for the chance to make a real and tangible impact. Does this sound like you? We Want You!SimilarWeb continues to grow rapidly and globally. Therefore, it is crucial to scale our operation and equip our global go-to-market employees with the knowledge and skills necessary to succeed in their roles."}