{"jobID": "2803081026", "jobLocation": "San_Francisco_CA", "jobTitle": "Senior HRBP - Technology", "companyRating": null, "companyInfo": {"Website": "www.wework.com", "Headquarters": "New York, NY", "Size": "1001 to 5000 employees", "Founded": " 2010", "Type": " Company - Private", "Industry": " Business Services", "Revenue": " Unknown / Non-Applicable", "Competitors": " Unknown"}, "estimatedSalary": null, "jobDescription": " WeWork is the platform for creators, providing hundreds of thousands of members across the globe with space, community, and services that allow them to do what they love and craft their life's work. Our mission is to build a world where people work to make a life, not just a living, and our team members are central to that goal.  WeWork is crafting a layer of technology to power our vision of space as a service. From identifying and building a new location to bringing that space to market in a flexible, easy-to-consume way, to seamlessly operating these spaces to delight our members, we are making state-of-the-art systems to automate, optimize, and improve the experience. The data we are collecting is being used to dynamically tune utilization, pricing, even layout and form factor. This technology advantage has allowed WeWork to scale to 200+ buildings in 20+ counties and will be our competitive advantage as the company continues to grow.  Are you someone with an active, creative streak? Do you love fast-paced, exciting environments? Are you looking to contribute to making a real impact on many different communities and cultures around the world with the work that you're doing? If so, then we may have the opportunity for you.Abouttheposition"}